photologue_addons
