Metadata-Version: 1.0
Name: django-photologue-addons
Version: 0.2.2
Summary: An extension to the base photologue template tag set.
Home-page: http://github.com/powellc/django-photologue-addons
Author: Colin Powell
Author-email: colin@onecardinal.com
License: BSD
Download-URL: http://github.com/powellc/django-photologue-addons/downloads
Platform: UNKNOWN
Classifier: Development Status :: 4 - Beta
Classifier: Environment :: Web Environment
Classifier: Intended Audience :: Developers
Classifier: License :: OSI Approved :: BSD License
Classifier: Operating System :: OS Independent
Classifier: Programming Language :: Python
Classifier: Framework :: Django
